airflow/providers/trino/__init__.py
airflow/providers/trino/get_provider_info.py
airflow/providers/trino/version_compat.py
airflow/providers/trino/assets/__init__.py
airflow/providers/trino/assets/trino.py
airflow/providers/trino/hooks/__init__.py
airflow/providers/trino/hooks/trino.py
airflow/providers/trino/transfers/__init__.py
airflow/providers/trino/transfers/gcs_to_trino.py
apache_airflow_providers_trino-6.4.2.dist-info/entry_points.txt
apache_airflow_providers_trino-6.4.2.dist-info/licenses/LICENSE
apache_airflow_providers_trino-6.4.2.dist-info/licenses/NOTICE
apache_airflow_providers_trino-6.4.2.dist-info/WHEEL
apache_airflow_providers_trino-6.4.2.dist-info/METADATA
apache_airflow_providers_trino-6.4.2.dist-info/RECORD
