Metadata-Version: 2.4
Name: apache-airflow-providers-trino
Version: 6.4.2
Summary: Provider package apache-airflow-providers-trino for Apache Airflow
Keywords: airflow-provider,trino,airflow,integration
Author-email: Apache Software Foundation <dev@airflow.apache.org>
Maintainer-email: Apache Software Foundation <dev@airflow.apache.org>
Requires-Python: >=3.10
License-Expression: Apache-2.0
Classifier: Development Status :: 5 - Production/Stable
Classifier: Environment :: Console
Classifier: Environment :: Web Environment
Classifier: Intended Audience :: Developers
Classifier: Intended Audience :: System Administrators
Classifier: Framework :: Apache Airflow
Classifier: Framework :: Apache Airflow :: Provider
Classifier: Programming Language :: Python :: 3.10
Classifier: Programming Language :: Python :: 3.11
Classifier: Programming Language :: Python :: 3.12
Classifier: Programming Language :: Python :: 3.13
Classifier: Topic :: System :: Monitoring
License-File: LICENSE
License-File: NOTICE
Requires-Dist: apache-airflow>=2.11.0
Requires-Dist: apache-airflow-providers-common-compat>=1.12.0
Requires-Dist: apache-airflow-providers-common-sql>=1.20.0
Requires-Dist: pandas>=2.1.2; python_version <"3.13"
Requires-Dist: pandas>=2.2.3; python_version >="3.13"
Requires-Dist: trino>=0.319.0
Requires-Dist: apache-airflow-providers-google ; extra == "google"
Requires-Dist: apache-airflow-providers-openlineage ; extra == "openlineage"
Project-URL: Bug Tracker, https://github.com/apache/airflow/issues
Project-URL: Changelog, https://airflow.apache.org/docs/apache-airflow-providers-trino/6.4.2/changelog.html
Project-URL: Documentation, https://airflow.apache.org/docs/apache-airflow-providers-trino/6.4.2
Project-URL: Mastodon, https://fosstodon.org/@airflow
Project-URL: Slack Chat, https://s.apache.org/airflow-slack
Project-URL: Source Code, https://github.com/apache/airflow
Project-URL: YouTube, https://www.youtube.com/channel/UCSXwxpWZQ7XZ1WL3wqevChA/
Provides-Extra: google
Provides-Extra: openlineage
